usyd_colors/__init__.py
usyd_colors/palette_data.py
usyd_colors/palettes.py
usyd_colors-0.1.0.dist-info/METADATA
usyd_colors-0.1.0.dist-info/WHEEL
usyd_colors-0.1.0.dist-info/RECORD
