Metadata-Version: 2.1
Name: usyd-colors
Version: 0.1.0
Summary: A package containing various palettes inspired by the colors of The University of Sydney.
Author: Luke Thompson
Author-email: luke-a-thompson@outlook.com
Requires-Python: >=3.10,<4.0
Classifier: Programming Language :: Python :: 3
Classifier: Programming Language :: Python :: 3.10
Classifier: Programming Language :: Python :: 3.11
Classifier: Programming Language :: Python :: 3.12
Provides-Extra: matplotlib
